[
  {
    "id": 1,
    "first_name": "Willetta",
    "last_name": "Tace",
    "email": "wtace0@tuttocitta.it"
  },
  {
    "id": 2,
    "first_name": "Natal",
    "last_name": "Geke",
    "email": "ngeke1@eventbrite.com"
  },
  {
    "id": 3,
    "first_name": "Cord",
    "last_name": "Candie",
    "email": "ccandie2@smugmug.com"
  },
  {
    "id": 4,
    "first_name": "Sansone",
    "last_name": "Bernardi",
    "email": "sbernardi3@chron.com"
  },
  {
    "id": 5,
    "first_name": "Whitman",
    "last_name": "Wrightham",
    "email": "wwrightham4@wordpress.org"
  },
  {
    "id": 6,
    "first_name": "Guthry",
    "last_name": "Curtoys",
    "email": "gcurtoys5@hp.com"
  },
  {
    "id": 7,
    "first_name": "Adler",
    "last_name": "Widdowes",
    "email": "awiddowes6@nytimes.com"
  },
  {
    "id": 8,
    "first_name": "Yanaton",
    "last_name": "Labes",
    "email": "ylabes7@flickr.com"
  },
  {
    "id": 9,
    "first_name": "Crystal",
    "last_name": "Peascod",
    "email": "cpeascod8@state.tx.us"
  },
  {
    "id": 10,
    "first_name": "Susannah",
    "last_name": "Deeprose",
    "email": "sdeeprose9@cam.ac.uk"
  },
  {
    "id": 11,
    "first_name": "Valera",
    "last_name": "Bosanko",
    "email": "vbosankoa@ocn.ne.jp"
  },
  {
    "id": 12,
    "first_name": "Lexine",
    "last_name": "Ramsey",
    "email": "lramseyb@linkedin.com"
  },
  {
    "id": 13,
    "first_name": "Avril",
    "last_name": "Sellers",
    "email": "asellersc@prweb.com"
  },
  {
    "id": 14,
    "first_name": "Eldin",
    "last_name": "McRobb",
    "email": "emcrobbd@yelp.com"
  },
  {
    "id": 15,
    "first_name": "Conny",
    "last_name": "Canario",
    "email": "ccanarioe@uol.com.br"
  },
  {
    "id": 16,
    "first_name": "Christabella",
    "last_name": "Huie",
    "email": "chuief@fotki.com"
  },
  {
    "id": 17,
    "first_name": "Rossie",
    "last_name": "Bardill",
    "email": "rbardillg@hc360.com"
  },
  {
    "id": 18,
    "first_name": "Lucian",
    "last_name": "Dachey",
    "email": "ldacheyh@soundcloud.com"
  },
  {
    "id": 19,
    "first_name": "Whittaker",
    "last_name": "Karmel",
    "email": "wkarmeli@fotki.com"
  },
  {
    "id": 20,
    "first_name": "Daria",
    "last_name": "Pridmore",
    "email": "dpridmorej@spotify.com"
  },
  {
    "id": 21,
    "first_name": "Allene",
    "last_name": "Sharpley",
    "email": "asharpleyk@quantcast.com"
  },
  {
    "id": 22,
    "first_name": "Kingsley",
    "last_name": "Wicklen",
    "email": "kwicklenl@forbes.com"
  },
  {
    "id": 23,
    "first_name": "Koressa",
    "last_name": "Heed",
    "email": "kheedm@tamu.edu"
  },
  {
    "id": 24,
    "first_name": "Leonidas",
    "last_name": "Dopson",
    "email": "ldopsonn@google.cn"
  },
  {
    "id": 25,
    "first_name": "Carly",
    "last_name": "Dalgety",
    "email": "cdalgetyo@blog.com"
  },
  {
    "id": 26,
    "first_name": "Naomi",
    "last_name": "Wraith",
    "email": "nwraithp@hexun.com"
  },
  {
    "id": 27,
    "first_name": "Leesa",
    "last_name": "Budge",
    "email": "lbudgeq@shinystat.com"
  },
  {
    "id": 28,
    "first_name": "Gorden",
    "last_name": "Paddell",
    "email": "gpaddellr@dropbox.com"
  },
  {
    "id": 29,
    "first_name": "Janene",
    "last_name": "Blakeborough",
    "email": "jblakeboroughs@webmd.com"
  },
  {
    "id": 30,
    "first_name": "Abba",
    "last_name": "Wastall",
    "email": "awastallt@free.fr"
  },
  {
    "id": 31,
    "first_name": "Amble",
    "last_name": "Grayland",
    "email": "agraylandu@hostgator.com"
  },
  {
    "id": 32,
    "first_name": "Vincenty",
    "last_name": "Chaimson",
    "email": "vchaimsonv@salon.com"
  },
  {
    "id": 33,
    "first_name": "Otho",
    "last_name": "Baack",
    "email": "obaackw@boston.com"
  },
  {
    "id": 34,
    "first_name": "Locke",
    "last_name": "Eckley",
    "email": "leckleyx@wired.com"
  },
  {
    "id": 35,
    "first_name": "Findley",
    "last_name": "Fenimore",
    "email": "ffenimorey@qq.com"
  },
  {
    "id": 36,
    "first_name": "Wynne",
    "last_name": "Katz",
    "email": "wkatzz@shareasale.com"
  },
  {
    "id": 37,
    "first_name": "Marjy",
    "last_name": "Leith",
    "email": "mleith10@1688.com"
  },
  {
    "id": 38,
    "first_name": "Drucill",
    "last_name": "Fourmy",
    "email": "dfourmy11@nymag.com"
  },
  {
    "id": 39,
    "first_name": "Lorrie",
    "last_name": "Andrejs",
    "email": "landrejs12@cyberchimps.com"
  },
  {
    "id": 40,
    "first_name": "Dannie",
    "last_name": "Ahern",
    "email": "dahern13@va.gov"
  },
  {
    "id": 41,
    "first_name": "Alysia",
    "last_name": "Cunniam",
    "email": "acunniam14@blogs.com"
  },
  {
    "id": 42,
    "first_name": "Joice",
    "last_name": "Keatch",
    "email": "jkeatch15@blogspot.com"
  },
  {
    "id": 43,
    "first_name": "Nathalie",
    "last_name": "Kennealy",
    "email": "nkennealy16@4shared.com"
  },
  {
    "id": 44,
    "first_name": "Maxie",
    "last_name": "Luparti",
    "email": "mluparti17@google.com"
  },
  {
    "id": 45,
    "first_name": "Ian",
    "last_name": "Duffy",
    "email": "iduffy18@squidoo.com"
  },
  {
    "id": 46,
    "first_name": "Benn",
    "last_name": "Gaffer",
    "email": "bgaffer19@hostgator.com"
  },
  {
    "id": 47,
    "first_name": "Roley",
    "last_name": "Cree",
    "email": "rcree1a@homestead.com"
  },
  {
    "id": 48,
    "first_name": "Lurlene",
    "last_name": "Threadkell",
    "email": "lthreadkell1b@weebly.com"
  },
  {
    "id": 49,
    "first_name": "Ali",
    "last_name": "D'Aubney",
    "email": "adaubney1c@over-blog.com"
  },
  {
    "id": 50,
    "first_name": "Bondy",
    "last_name": "Plevey",
    "email": "bplevey1d@cnet.com"
  },
  {
    "id": 51,
    "first_name": "Aura",
    "last_name": "Pybus",
    "email": "apybus1e@liveinternet.ru"
  },
  {
    "id": 52,
    "first_name": "Hayyim",
    "last_name": "Habble",
    "email": "hhabble1f@theatlantic.com"
  },
  {
    "id": 53,
    "first_name": "Roger",
    "last_name": "Hitzmann",
    "email": "rhitzmann1g@youtu.be"
  },
  {
    "id": 54,
    "first_name": "Patton",
    "last_name": "Markova",
    "email": "pmarkova1h@360.cn"
  },
  {
    "id": 55,
    "first_name": "Constantino",
    "last_name": "Culpan",
    "email": "cculpan1i@weebly.com"
  },
  {
    "id": 56,
    "first_name": "Frederica",
    "last_name": "Milius",
    "email": "fmilius1j@mac.com"
  },
  {
    "id": 57,
    "first_name": "Marianna",
    "last_name": "Itter",
    "email": "mitter1k@marriott.com"
  },
  {
    "id": 58,
    "first_name": "Arleen",
    "last_name": "Wailes",
    "email": "awailes1l@dot.gov"
  },
  {
    "id": 59,
    "first_name": "Filippa",
    "last_name": "Goatcher",
    "email": "fgoatcher1m@qq.com"
  },
  {
    "id": 60,
    "first_name": "Roberta",
    "last_name": "Tyson",
    "email": "rtyson1n@ihg.com"
  },
  {
    "id": 61,
    "first_name": "Cloe",
    "last_name": "Fortman",
    "email": "cfortman1o@comcast.net"
  },
  {
    "id": 62,
    "first_name": "Dennet",
    "last_name": "McGrill",
    "email": "dmcgrill1p@shareasale.com"
  },
  {
    "id": 63,
    "first_name": "Beauregard",
    "last_name": "Iggalden",
    "email": "biggalden1q@europa.eu"
  },
  {
    "id": 64,
    "first_name": "Fulvia",
    "last_name": "Rugieri",
    "email": "frugieri1r@youtu.be"
  },
  {
    "id": 65,
    "first_name": "Tony",
    "last_name": "Tapply",
    "email": "ttapply1s@nba.com"
  },
  {
    "id": 66,
    "first_name": "Olly",
    "last_name": "Minchinden",
    "email": "ominchinden1t@tripod.com"
  },
  {
    "id": 67,
    "first_name": "Nap",
    "last_name": "Mackett",
    "email": "nmackett1u@howstuffworks.com"
  },
  {
    "id": 68,
    "first_name": "Katya",
    "last_name": "Supple",
    "email": "ksupple1v@ovh.net"
  },
  {
    "id": 69,
    "first_name": "Matias",
    "last_name": "Lade",
    "email": "mlade1w@patch.com"
  },
  {
    "id": 70,
    "first_name": "Lurette",
    "last_name": "Mattson",
    "email": "lmattson1x@privacy.gov.au"
  },
  {
    "id": 71,
    "first_name": "Nolana",
    "last_name": "Grayer",
    "email": "ngrayer1y@reddit.com"
  },
  {
    "id": 72,
    "first_name": "Dillon",
    "last_name": "Northage",
    "email": "dnorthage1z@bizjournals.com"
  },
  {
    "id": 73,
    "first_name": "Leigh",
    "last_name": "Gwinnel",
    "email": "lgwinnel20@youtu.be"
  },
  {
    "id": 74,
    "first_name": "Emalee",
    "last_name": "Silvermann",
    "email": "esilvermann21@ftc.gov"
  },
  {
    "id": 75,
    "first_name": "Mallorie",
    "last_name": "Risbridge",
    "email": "mrisbridge22@usda.gov"
  },
  {
    "id": 76,
    "first_name": "Ingram",
    "last_name": "Lefridge",
    "email": "ilefridge23@harvard.edu"
  },
  {
    "id": 77,
    "first_name": "Elisabetta",
    "last_name": "Chinnick",
    "email": "echinnick24@fc2.com"
  },
  {
    "id": 78,
    "first_name": "Dal",
    "last_name": "Slocomb",
    "email": "dslocomb25@bluehost.com"
  },
  {
    "id": 79,
    "first_name": "Audra",
    "last_name": "MacLice",
    "email": "amaclice26@friendfeed.com"
  },
  {
    "id": 80,
    "first_name": "Peyton",
    "last_name": "Scates",
    "email": "pscates27@meetup.com"
  },
  {
    "id": 81,
    "first_name": "Melvyn",
    "last_name": "Cisland",
    "email": "mcisland28@exblog.jp"
  },
  {
    "id": 82,
    "first_name": "Rhona",
    "last_name": "Cadagan",
    "email": "rcadagan29@yellowpages.com"
  },
  {
    "id": 83,
    "first_name": "Saleem",
    "last_name": "Nichol",
    "email": "snichol2a@hud.gov"
  },
  {
    "id": 84,
    "first_name": "Paolina",
    "last_name": "Lashley",
    "email": "plashley2b@foxnews.com"
  },
  {
    "id": 85,
    "first_name": "Jessey",
    "last_name": "Hitschke",
    "email": "jhitschke2c@wordpress.org"
  },
  {
    "id": 86,
    "first_name": "Hildegaard",
    "last_name": "Pughe",
    "email": "hpughe2d@samsung.com"
  },
  {
    "id": 87,
    "first_name": "Orly",
    "last_name": "Ohms",
    "email": "oohms2e@cpanel.net"
  },
  {
    "id": 88,
    "first_name": "Phineas",
    "last_name": "Feld",
    "email": "pfeld2f@so-net.ne.jp"
  },
  {
    "id": 89,
    "first_name": "Bertie",
    "last_name": "Solley",
    "email": "bsolley2g@nhs.uk"
  },
  {
    "id": 90,
    "first_name": "Shanie",
    "last_name": "Bettridge",
    "email": "sbettridge2h@de.vu"
  },
  {
    "id": 91,
    "first_name": "Tris",
    "last_name": "Sayton",
    "email": "tsayton2i@pagesperso-orange.fr"
  },
  {
    "id": 92,
    "first_name": "Shandeigh",
    "last_name": "Shaw",
    "email": "sshaw2j@independent.co.uk"
  },
  {
    "id": 93,
    "first_name": "Roberta",
    "last_name": "Ketchen",
    "email": "rketchen2k@networkadvertising.org"
  },
  {
    "id": 94,
    "first_name": "Cortney",
    "last_name": "Shilstone",
    "email": "cshilstone2l@state.tx.us"
  },
  {
    "id": 95,
    "first_name": "Tiffi",
    "last_name": "Andreotti",
    "email": "tandreotti2m@t.co"
  },
  {
    "id": 96,
    "first_name": "Boony",
    "last_name": "Worthington",
    "email": "bworthington2n@barnesandnoble.com"
  },
  {
    "id": 97,
    "first_name": "Petrina",
    "last_name": "Quarmby",
    "email": "pquarmby2o@oakley.com"
  },
  {
    "id": 98,
    "first_name": "Demetrius",
    "last_name": "Cargill",
    "email": "dcargill2p@vk.com"
  },
  {
    "id": 99,
    "first_name": "Edgardo",
    "last_name": "Novotne",
    "email": "enovotne2q@illinois.edu"
  },
  {
    "id": 100,
    "first_name": "Von",
    "last_name": "Chape",
    "email": "vchape2r@psu.edu"
  }
]
